TA_Lib_Precompiled.libs/libta_lib-cf6da1c6.so.0.0.0
talib/abstract.py
talib/stream.py
talib/test_func.py
talib/deprecated.py
talib/test_abstract.py
talib/_ta_lib.cpython-310-x86_64-linux-gnu.so
talib/test_pandas.py
talib/test_data.py
talib/test_polars.py
talib/test_stream.py
talib/__init__.py
TA_Lib_Precompiled-0.4.25.dist-info/AUTHORS
TA_Lib_Precompiled-0.4.25.dist-info/LICENSE
TA_Lib_Precompiled-0.4.25.dist-info/top_level.txt
TA_Lib_Precompiled-0.4.25.dist-info/WHEEL
TA_Lib_Precompiled-0.4.25.dist-info/RECORD
TA_Lib_Precompiled-0.4.25.dist-info/METADATA
