Metadata-Version: 2.1
Name: TA-Lib-Precompiled
Version: 0.4.25
Summary: Python wrapper for TA-Lib
Home-page: https://github.com/minggnim/ta-lib
Download-URL: https://github.com/minggnim/ta-lib/releases
Author: John Benediktsson
Author-email: mrjbq7@gmail.com
License: BSD
Classifier: License :: OSI Approved :: BSD License
Classifier: Development Status :: 5 - Production/Stable
Classifier: Operating System :: Unix
Classifier: Operating System :: POSIX
Classifier: Operating System :: MacOS :: MacOS X
Classifier: Operating System :: Microsoft :: Windows
Classifier: Programming Language :: Python :: 3.8
Classifier: Programming Language :: Python :: 3.9
Classifier: Programming Language :: Python :: 3.10
Classifier: Programming Language :: Python :: 3.11
Classifier: Programming Language :: Cython
Classifier: Topic :: Office/Business :: Financial
Classifier: Topic :: Scientific/Engineering :: Mathematics
Classifier: Intended Audience :: Developers
Classifier: Intended Audience :: Science/Research
Classifier: Intended Audience :: Financial and Insurance Industry
License-File: LICENSE
License-File: AUTHORS
Requires-Dist: numpy
